
[
  {
    "text": "چای سیاه پُردم مخصوص شب‌نشینی با عطر دارچین",
    "category": "food_drink",
    "subcategory": "seasonal_cultural_specials",
    "preferencesJson": {
      "temp_extreme_cold": 1.0,
      "temp_cold": 0.8,
      "temp_cool": 0.6,
      "temp_hot": -0.9,
      "weather_cloudy": 0.6,
      "weather_rain": 0.8,
      "weather_snow": 0.9,
      "time_evening": 0.9,
      "time_night": 0.8,
      "season_winter": 0.9,
      "season_autumn": 0.7,
      "day_weekend": 0.5,
      "cultural_tradition": 0.9,
      "social_group": 0.6,
      "social_family": 0.5,
      "mood_relaxed": 0.7,
      "mood_nostalgic": 0.8,
      "location_indoor": 0.9,
      "location_home": 0.8,
      "energy_low": 0.4
    }
  },
  {
    "text": "سینی انار و هندوانه برای شب‌های بلند",
    "category": "food_drink",
    "subcategory": "seasonal_cultural_specials",
    "preferencesJson": {
      "temp_cold": 0.6,
      "temp_cool": 0.5,
      "temp_hot": -0.7,
      "weather_clear": 0.4,
      "weather_cloudy": 0.3,
      "time_evening": 0.8,
      "time_night": 0.9,
      "season_winter": 0.9,
      "season_autumn": 0.6,
      "day_holiday_eve": 0.8,
      "cultural_tradition": 1.0,
      "social_family": 0.7,
      "social_group": 0.6,
      "mood_nostalgic": 0.8,
      "mood_happy": 0.6,
      "location_home": 0.8,
      "location_indoor": 0.7,
      "energy_medium": 0.4
    }
  },
  {
    "text": "آجیل هفت‌مغز اعلاء برای جشن‌ها",
    "category": "food_drink",
    "subcategory": "seasonal_cultural_specials",
    "preferencesJson": {
      "temp_warm": 0.5,
      "temp_cool": 0.4,
      "weather_clear": 0.3,
      "weather_partly_cloudy": 0.3,
      "time_evening": 0.7,
      "day_holiday": 0.9,
      "day_weekend": 0.7,
      "season_winter": 0.6,
      "season_spring": 0.5,
      "season_autumn": 0.5,
      "cultural_tradition": 0.9,
      "social_group": 0.7,
      "social_family": 0.6,
      "social_friends": 0.6,
      "mood_happy": 0.7,
      "mood_energetic": 0.4,
      "location_indoor": 0.6,
      "energy_medium": 0.4
    }
  },
  {
    "text": "آش رشته بهاری با سبزی تازه و پیازداغ",
    "category": "food_drink",
    "subcategory": "seasonal_cultural_specials",
    "preferencesJson": {
      "temp_cold": 0.9,
      "temp_cool": 0.7,
      "temp_hot": -0.8,
      "weather_cloudy": 0.5,
      "weather_rain": 0.7,
      "time_afternoon": 0.7,
      "time_evening": 0.8,
      "season_spring": 1.0,
      "season_autumn": 0.6,
      "cultural_tradition": 0.8,
      "social_family": 0.7,
      "social_group": 0.6,
      "mood_relaxed": 0.5,
      "mood_sad": 0.4,
      "location_indoor": 0.9,
      "location_home": 0.8,
      "energy_low": 0.3,
      "energy_medium": 0.4
    }
  },
  {
    "text": "شربت سکنجبین خنک با خیار و نعنا",
    "category": "food_drink",
    "subcategory": "seasonal_cultural_specials",
    "preferencesJson": {
      "temp_hot": 1.0,
      "temp_warm": 0.8,
      "temp_cold": -0.9,
      "weather_clear": 1.0,
      "weather_partly_cloudy": 0.7,
      "humidity_dry": 0.7,
      "time_afternoon": 0.9,
      "season_summer": 1.0,
      "season_spring": 0.5,
      "cultural_tradition": 0.6,
      "social_family": 0.5,
      "social_friends": 0.5,
      "mood_happy": 0.6,
      "mood_energetic": 0.5,
      "location_outdoor": 0.7,
      "energy_high": 0.4
    }
  },
  {
    "text": "فالوده شیرازی با آب‌لیمو و گلاب",
    "category": "food_drink",
    "subcategory": "seasonal_cultural_specials",
    "preferencesJson": {
      "temp_hot": 1.0,
      "temp_warm": 0.8,
      "temp_cold": -1.0,
      "weather_clear": 0.9,
      "weather_partly_cloudy": 0.7,
      "humidity_dry": 0.6,
      "time_afternoon": 0.8,
      "season_summer": 1.0,
      "season_spring": 0.4,
      "cultural_tradition": 0.7,
      "social_friends": 0.6,
      "social_group": 0.5,
      "mood_happy": 0.7,
      "location_outdoor": 0.6,
      "energy_medium": 0.4
    }
  },
  {
    "text": "هندوانه خنک با گلاب برای روزهای گرم",
    "category": "food_drink",
    "subcategory": "seasonal_cultural_specials",
    "preferencesJson": {
      "temp_hot": 1.0,
      "temp_warm": 0.8,
      "temp_cold": -0.9,
      "weather_clear": 1.0,
      "weather_partly_cloudy": 0.7,
      "humidity_dry": 0.6,
      "time_afternoon": 0.9,
      "season_summer": 1.0,
      "season_spring": 0.4,
      "cultural_tradition": 0.5,
      "social_family": 0.5,
      "social_friends": 0.5,
      "mood_happy": 0.7,
      "location_outdoor": 0.7,
      "energy_medium": 0.4
    }
  },
  {
    "text": "نان برنجی خوش‌عطر با تخم‌خرفه",
    "category": "food_drink",
    "subcategory": "seasonal_cultural_specials",
    "preferencesJson": {
      "temp_cool": 0.5,
      "temp_cold": 0.6,
      "weather_cloudy": 0.4,
      "weather_rain": 0.5,
      "weather_snow": 0.6,
      "time_evening": 0.6,
      "time_night": 0.5,
      "season_winter": 0.6,
      "season_autumn": 0.5,
      "cultural_tradition": 0.7,
      "day_weekend": 0.4,
      "social_family": 0.5,
      "social_group": 0.5,
      "mood_nostalgic": 0.6,
      "mood_happy": 0.4,
      "location_indoor": 0.6,
      "energy_low": 0.3
    }
  },
  {
    "text": "کدوحلوایی شیرین با دارچین برای عصرهای پاییز",
    "category": "food_drink",
    "subcategory": "seasonal_cultural_specials",
    "preferencesJson": {
      "temp_cold": 0.8,
      "temp_cool": 0.7,
      "temp_hot": -0.8,
      "weather_cloudy": 0.6,
      "weather_rain": 0.7,
      "time_afternoon": 0.7,
      "time_evening": 0.8,
      "season_autumn": 1.0,
      "season_winter": 0.7,
      "cultural_tradition": 0.8,
      "social_family": 0.6,
      "social_group": 0.5,
      "mood_relaxed": 0.6,
      "mood_nostalgic": 0.7,
      "location_home": 0.7,
      "location_indoor": 0.8,
      "energy_low": 0.3
    }
  },
  {
    "text": "چغندر داغ (لبو) با گلپر برای روزهای سرد",
    "category": "food_drink",
    "subcategory": "seasonal_cultural_specials",
    "preferencesJson": {
      "temp_extreme_cold": 1.0,
      "temp_cold": 0.9,
      "temp_hot": -1.0,
      "weather_snow": 0.9,
      "weather_rain": 0.7,
      "weather_cloudy": 0.6,
      "time_evening": 0.6,
      "time_night": 0.5,
      "season_winter": 1.0,
      "season_autumn": 0.6,
      "cultural_tradition": 0.7,
      "social_solo": 0.4,
      "social_family": 0.5,
      "mood_relaxed": 0.5,
      "mood_nostalgic": 0.6,
      "location_outdoor": 0.4,
      "location_home": 0.6,
      "energy_low": 0.3
    }
  },
  {
    "text": "شربت ریواس ترش و خنک",
    "category": "food_drink",
    "subcategory": "seasonal_cultural_specials",
    "preferencesJson": {
      "temp_hot": 1.0,
      "temp_warm": 0.8,
      "temp_cold": -0.8,
      "weather_clear": 0.9,
      "weather_partly_cloudy": 0.7,
      "humidity_dry": 0.7,
      "time_afternoon": 0.8,
      "season_summer": 1.0,
      "season_spring": 0.6,
      "cultural_tradition": 0.6,
      "social_friends": 0.5,
      "social_group": 0.4,
      "mood_happy": 0.6,
      "location_outdoor": 0.6,
      "energy_medium": 0.4
    }
  },
  {
    "text": "شیره خرما با نان تازه و کره محلی",
    "category": "food_drink",
    "subcategory": "seasonal_cultural_specials",
    "preferencesJson": {
      "temp_cool": 0.6,
      "temp_cold": 0.8,
      "temp_hot": -0.9,
      "weather_cloudy": 0.5,
      "weather_rain": 0.6,
      "time_morning": 0.6,
      "time_afternoon": 0.5,
      "season_winter": 0.8,
      "season_autumn": 0.6,
      "cultural_tradition": 0.7,
      "social_family": 0.6,
      "social_group": 0.5,
      "mood_relaxed": 0.5,
      "mood_happy": 0.4,
      "location_home": 0.7,
      "location_indoor": 0.7,
      "energy_medium": 0.4
    }
  },
  {
    "text": "سوهان اصیل و ترد",
    "category": "food_drink",
    "subcategory": "seasonal_cultural_specials",
    "preferencesJson": {
      "temp_warm": 0.5,
      "temp_cool": 0.4,
      "weather_clear": 0.3,
      "weather_partly_cloudy": 0.3,
      "time_evening": 0.6,
      "day_holiday": 0.7,
      "season_winter": 0.5,
      "season_autumn": 0.4,
      "season_spring": 0.4,
      "cultural_tradition": 0.8,
      "social_group": 0.6,
      "social_family": 0.5,
      "mood_happy": 0.6,
      "location_indoor": 0.5,
      "energy_medium": 0.3
    }
  },
  {
    "text": "باقلوا یزدی با پسته و هل",
    "category": "food_drink",
    "subcategory": "seasonal_cultural_specials",
    "preferencesJson": {
      "temp_cool": 0.6,
      "temp_cold": 0.7,
      "weather_cloudy": 0.5,
      "weather_rain": 0.6,
      "time_evening": 0.7,
      "day_holiday": 0.9,
      "season_winter": 0.6,
      "season_autumn": 0.5,
      "cultural_tradition": 0.9,
      "social_family": 0.6,
      "social_group": 0.6,
      "mood_happy": 0.7,
      "mood_nostalgic": 0.5,
      "location_indoor": 0.6,
      "energy_low": 0.3
    }
  },
  {
    "text": "چای گل‌محمدی برای دورهمی‌های خانوادگی",
    "category": "food_drink",
    "subcategory": "seasonal_cultural_specials",
    "preferencesJson": {
      "temp_cold": 0.8,
      "temp_cool": 0.6,
      "temp_hot": -0.8,
      "weather_cloudy": 0.6,
      "weather_rain": 0.7,
      "time_evening": 0.8,
      "season_winter": 0.7,
      "season_autumn": 0.5,
      "cultural_tradition": 0.8,
      "social_family": 0.8,
      "social_group": 0.6,
      "mood_relaxed": 0.6,
      "mood_happy": 0.5,
      "location_home": 0.7,
      "location_indoor": 0.8,
      "energy_low": 0.3
    }
  },
  {
    "text": "باقلای تازه با گلپر و نمک",
    "category": "food_drink",
    "subcategory": "seasonal_cultural_specials",
    "preferencesJson": {
      "temp_warm": 0.6,
      "temp_cool": 0.4,
      "weather_clear": 0.4,
      "weather_partly_cloudy": 0.3,
      "time_afternoon": 0.6,
      "season_spring": 1.0,
      "season_summer": 0.5,
      "cultural_tradition": 0.6,
      "social_solo": 0.4,
      "social_family": 0.4,
      "mood_happy": 0.5,
      "location_outdoor": 0.5,
      "energy_medium": 0.3
    }
  },
  {
    "text": "آجیل شیرین مخصوص شب‌نشینی",
    "category": "food_drink",
    "subcategory": "seasonal_cultural_specials",
    "preferencesJson": {
      "temp_cool": 0.5,
      "temp_cold": 0.6,
      "weather_cloudy": 0.4,
      "weather_rain": 0.5,
      "time_evening": 0.7,
      "time_night": 0.8,
      "season_autumn": 0.6,
      "season_winter": 0.6,
      "cultural_tradition": 0.9,
      "social_group": 0.7,
      "social_family": 0.6,
      "mood_happy": 0.6,
      "mood_nostalgic": 0.5,
      "location_home": 0.7,
      "location_indoor": 0.7,
      "energy_low": 0.3
    }
  },
  {
    "text": "آش انار با گلپر برای روزهای ابری",
    "category": "food_drink",
    "subcategory": "seasonal_cultural_specials",
    "preferencesJson": {
      "temp_cold": 0.8,
      "temp_cool": 0.6,
      "temp_hot": -0.8,
      "weather_cloudy": 1.0,
      "weather_rain": 0.7,
      "time_afternoon": 0.7,
      "time_evening": 0.7,
      "season_autumn": 0.9,
      "season_winter": 0.8,
      "cultural_tradition": 0.8,
      "social_family": 0.6,
      "social_group": 0.5,
      "mood_relaxed": 0.5,
      "mood_nostalgic": 0.6,
      "location_indoor": 0.9,
      "energy_low": 0.3
    }
  },
  {
    "text": "شربت بیدمشک معطر و خنک",
    "category": "food_drink",
    "subcategory": "seasonal_cultural_specials",
    "preferencesJson": {
      "temp_hot": 1.0,
      "temp_warm": 0.8,
      "temp_cold": -0.8,
      "weather_clear": 0.9,
      "weather_partly_cloudy": 0.6,
      "humidity_dry": 0.6,
      "time_afternoon": 0.8,
      "season_summer": 1.0,
      "season_spring": 0.5,
      "cultural_tradition": 0.6,
      "social_friends": 0.5,
      "social_family": 0.4,
      "mood_happy": 0.6,
      "location_outdoor": 0.6,
      "energy_medium": 0.4
    }
  },
  {
    "text": "نان‌قندی نرم و تازه",
    "category": "food_drink",
    "subcategory": "seasonal_cultural_specials",
    "preferencesJson": {
      "temp_cool": 0.5,
      "temp_cold": 0.6,
      "weather_cloudy": 0.4,
      "weather_rain": 0.4,
      "time_morning": 0.6,
      "time_evening": 0.5,
      "season_autumn": 0.5,
      "season_winter": 0.5,
      "cultural_tradition": 0.6,
      "day_holiday": 0.6,
      "social_family": 0.5,
      "social_group": 0.4,
      "mood_happy": 0.5,
      "location_indoor": 0.6,
      "energy_low": 0.3
    }
  },
  {
    "text": "آش رشته غلیظ و جاافتاده",
    "category": "food_drink",
    "subcategory": "seasonal_cultural_specials",
    "preferencesJson": {
      "temp_extreme_cold": 1.0,
      "temp_cold": 0.9,
      "temp_hot": -1.0,
      "weather_snow": 0.9,
      "weather_rain": 0.7,
      "weather_cloudy": 0.6,
      "time_afternoon": 0.7,
      "time_evening": 0.8,
      "season_winter": 1.0,
      "season_autumn": 0.7,
      "cultural_tradition": 0.9,
      "social_family": 0.8,
      "social_group": 0.7,
      "mood_relaxed": 0.6,
      "mood_sad": 0.5,
      "location_indoor": 0.9,
      "energy_low": 0.3
    }
  },
  {
    "text": "خاکشیر یخی با گلاب",
    "category": "food_drink",
    "subcategory": "seasonal_cultural_specials",
    "preferencesJson": {
      "temp_hot": 1.0,
      "temp_warm": 0.8,
      "temp_cold": -0.9,
      "weather_clear": 1.0,
      "humidity_dry": 0.7,
      "time_afternoon": 0.8,
      "season_summer": 1.0,
      "season_spring": 0.5,
      "cultural_tradition": 0.5,
      "social_solo": 0.4,
      "social_family": 0.4,
      "mood_happy": 0.5,
      "location_outdoor": 0.6,
      "energy_medium": 0.4
    }
  },
  {
    "text": "فالوده آلبالویی ترش و شیرین",
    "category": "food_drink",
    "subcategory": "seasonal_cultural_specials",
    "preferencesJson": {
      "temp_hot": 1.0,
      "temp_warm": 0.8,
      "temp_cold": -1.0,
      "weather_clear": 0.9,
      "weather_partly_cloudy": 0.7,
      "humidity_dry": 0.6,
      "time_afternoon": 0.8,
      "season_summer": 1.0,
      "season_spring": 0.4,
      "cultural_tradition": 0.7,
      "social_friends": 0.6,
      "social_group": 0.5,
      "mood_happy": 0.7,
      "location_outdoor": 0.6,
      "energy_medium": 0.4
    }
  },
  {
    "text": "کیک انار با دانه‌های یاقوتی",
    "category": "food_drink",
    "subcategory": "seasonal_cultural_specials",
    "preferencesJson": {
        "temp_cool": 0.5,
        "temp_cold": 0.6,
        "weather_cloudy": 0.4,
        "weather_rain": 0.5,
        "time_evening": 0.6,
        "time_night": 0.6,
        "season_autumn": 0.8,
        "season_winter": 0.7,
        "day_holiday": 0.8,
        "cultural_tradition": 0.8,
        "social_family": 0.6,
        "social_group": 0.6,
        "mood_happy": 0.6,
        "mood_nostalgic": 0.5,
        "location_indoor": 0.6,
        "energy_low": 0.3
    }
  },
  {
    "text": "باقلای بخارپز با سرکه و گلپر",
    "category": "food_drink",
    "subcategory": "seasonal_cultural_specials",
    "preferencesJson": {
      "temp_warm": 0.6,
      "temp_cool": 0.4,
      "weather_clear": 0.4,
      "weather_partly_cloudy": 0.3,
      "time_afternoon": 0.6,
      "season_spring": 1.0,
      "season_summer": 0.4,
      "cultural_tradition": 0.6,
      "social_family": 0.4,
      "social_solo": 0.4,
      "mood_happy": 0.5,
      "location_outdoor": 0.5,
      "energy_medium": 0.3
    }
  },
  {
    "text": "زولبیا و بامیه تازه و ترد",
    "category": "food_drink",
    "subcategory": "seasonal_cultural_specials",
    "preferencesJson": {
      "temp_cool": 0.5,
      "temp_cold": 0.6,
      "weather_cloudy": 0.4,
      "weather_rain": 0.5,
      "time_evening": 0.7,
      "season_ramadan": -10.0,
      "season_spring": 0.4,
      "season_autumn": 0.4,
      "cultural_tradition": 1.0,
      "day_holiday": 0.8,
      "social_group": 0.7,
      "social_family": 0.6,
      "mood_happy": 0.6,
      "location_indoor": 0.6,
      "energy_medium": 0.3
    }
  },
  {
    "text": "شله‌زرد زعفرانی با تزیین دارچین",
    "category": "food_drink",
    "subcategory": "seasonal_cultural_specials",
    "preferencesJson": {
      "temp_cool": 0.6,
      "temp_cold": 0.7,
      "weather_cloudy": 0.5,
      "weather_rain": 0.6,
      "time_evening": 0.7,
      "season_autumn": 0.6,
      "season_winter": 0.6,
      "day_holiday": 0.8,
      "cultural_tradition": 0.9,
      "social_family": 0.6,
      "social_group": 0.6,
      "mood_nostalgic": 0.6,
      "mood_happy": 0.5,
      "location_indoor": 0.7,
      "energy_low": 0.3
    }
  },
  {
    "text": "شیر برنج با عطر گلاب و مربای گل",
    "category": "food_drink",
    "subcategory": "seasonal_cultural_specials",
    "preferencesJson": {
      "temp_cool": 0.6,
      "temp_cold": 0.7,
      "weather_cloudy": 0.4,
      "weather_rain": 0.5,
      "time_evening": 0.6,
      "season_winter": 0.7,
      "season_autumn": 0.6,
      "cultural_tradition": 0.8,
      "social_family": 0.6,
      "social_group": 0.5,
      "mood_relaxed": 0.5,
      "mood_nostalgic": 0.6,
      "location_indoor": 0.7,
      "location_home": 0.6,
      "energy_low": 0.3
    }
  },
  {
    "text": "کیک زنجبیلی خانگی برای عصرانه",
    "category": "food_drink",
    "subcategory": "seasonal_cultural_specials",
    "preferencesJson": {
      "temp_cool": 0.5,
      "temp_cold": 0.6,
      "weather_cloudy": 0.4,
      "weather_rain": 0.5,
      "time_afternoon": 0.7,
      "time_evening": 0.6,
      "season_autumn": 0.7,
      "season_winter": 0.6,
      "cultural_tradition": 0.6,
      "social_family": 0.5,
      "social_group": 0.4,
      "mood_relaxed": 0.5,
      "location_indoor": 0.6,
      "energy_low": 0.3
    }
  },
  {
    "text": "شیرینی نخودچی لطیف با پسته",
    "category": "food_drink",
    "subcategory": "seasonal_cultural_specials",
    "preferencesJson": {
      "temp_cool": 0.5,
      "temp_cold": 0.6,
      "weather_cloudy": 0.4,
      "time_evening": 0.6,
      "season_spring": 0.5,
      "season_winter": 0.5,
      "day_holiday": 0.7,
      "cultural_tradition": 0.8,
      "social_family": 0.6,
      "social_group": 0.5,
      "mood_happy": 0.5,
      "mood_nostalgic": 0.5,
      "location_indoor": 0.6,
      "energy_low": 0.3
    }
  },
  {
    "text": "فالوده لیمویی خنک",
    "category": "food_drink",
    "subcategory": "seasonal_cultural_specials",
    "preferencesJson": {
      "temp_hot": 1.0,
      "temp_warm": 0.8,
      "temp_cold": -1.0,
      "weather_clear": 0.9,
      "weather_partly_cloudy": 0.6,
      "humidity_dry": 0.7,
      "time_afternoon": 0.8,
      "season_summer": 1.0,
      "season_spring": 0.4,
      "cultural_tradition": 0.6,
      "social_friends": 0.5,
      "mood_happy": 0.6,
      "location_outdoor": 0.6,
      "energy_medium": 0.4
    }
  },
  {
    "text": "آش جو سنتی برای جمع‌های صمیمی",
    "category": "food_drink",
    "subcategory": "seasonal_cultural_specials",
    "preferencesJson": {
      "temp_cold": 0.9,
      "temp_cool": 0.7,
      "temp_hot": -0.9,
      "weather_cloudy": 0.6,
      "weather_rain": 0.7,
      "time_evening": 0.7,
      "time_afternoon": 0.6,
      "season_winter": 0.9,
      "season_autumn": 0.7,
      "cultural_tradition": 0.8,
      "social_group": 0.7,
      "social_family": 0.6,
      "mood_relaxed": 0.5,
      "location_indoor": 0.9,
      "location_home": 0.7,
      "energy_low": 0.3
    }
  },
  {
    "text": "شربت انار تازه و طبیعی",
    "category": "food_drink",
    "subcategory": "seasonal_cultural_specials",
    "preferencesJson": {
      "temp_hot": 0.8,
      "temp_warm": 0.7,
      "temp_cold": -0.7,
      "weather_clear": 0.7,
      "weather_partly_cloudy": 0.5,
      "time_afternoon": 0.6,
      "season_autumn": 0.8,
      "season_summer": 0.4,
      "cultural_tradition": 0.6,
      "social_family": 0.4,
      "social_solo": 0.3,
      "mood_happy": 0.6,
      "location_outdoor": 0.5,
      "energy_medium": 0.4
    }
  },
  {
    "text": "کیک خرمایی با گردو و ادویه",
    "category": "food_drink",
    "subcategory": "seasonal_cultural_specials",
    "preferencesJson": {
      "temp_cold": 0.7,
      "temp_cool": 0.6,
      "weather_cloudy": 0.5,
      "weather_rain": 0.6,
      "time_evening": 0.6,
      "season_winter": 0.7,
      "season_autumn": 0.6,
      "cultural_tradition": 0.7,
      "social_family": 0.5,
      "social_group": 0.5,
      "mood_relaxed": 0.5,
      "mood_nostalgic": 0.5,
      "location_indoor": 0.7,
      "energy_low": 0.3
    }
  },
  {
    "text": "بستنی سنتی با تکه‌های خامه",
    "category": "food_drink",
    "subcategory": "seasonal_cultural_specials",
    "preferencesJson": {
      "temp_hot": 1.0,
      "temp_warm": 0.7,
      "temp_cold": -0.9,
      "weather_clear": 0.9,
      "humidity_dry": 0.6,
      "time_afternoon": 0.8,
      "season_summer": 1.0,
      "season_spring": 0.4,
      "cultural_tradition": 0.6,
      "social_friends": 0.5,
      "mood_happy": 0.6,
      "location_outdoor": 0.6,
      "energy_medium": 0.4
    }
  },
  {
    "text": "کدوبره شیرازی با عطر سبزیجات",
    "category": "food_drink",
    "subcategory": "seasonal_cultural_specials",
    "preferencesJson": {
      "temp_warm": 0.5,
      "temp_cool": 0.4,
      "weather_clear": 0.4,
      "weather_partly_cloudy": 0.3,
      "time_afternoon": 0.5,
      "season_spring": 0.8,
      "season_autumn": 0.5,
      "cultural_tradition": 0.7,
      "social_family": 0.4,
      "mood_relaxed": 0.5,
      "location_indoor": 0.5,
      "energy_low": 0.3
    }
  },
  {
    "text": "ماءالشعیر خانگی با گلاب و لیمو",
    "category": "food_drink",
    "subcategory": "seasonal_cultural_specials",
    "preferencesJson": {
      "temp_hot": 0.9,
      "temp_warm": 0.7,
      "temp_cold": -0.8,
      "weather_clear": 0.8,
      "weather_partly_cloudy": 0.6,
      "humidity_dry": 0.6,
      "time_afternoon": 0.7,
      "season_summer": 0.9,
      "season_spring": 0.5,
      "cultural_tradition": 0.5,
      "social_friends": 0.4,
      "mood_happy": 0.5,
      "location_outdoor": 0.6,
      "energy_medium": 0.4
    }
  },
  {
    "text": "شیر زعفرانی داغ و آرام‌بخش",
    "category": "food_drink",
    "subcategory": "seasonal_cultural_specials",
    "preferencesJson": {
      "temp_extreme_cold": 1.0,
      "temp_cold": 0.9,
      "temp_hot": -0.9,
      "weather_cloudy": 0.6,
      "weather_rain": 0.7,
      "time_evening": 0.8,
      "time_night": 0.7,
      "season_winter": 0.9,
      "season_autumn": 0.7,
      "cultural_tradition": 0.7,
      "social_family": 0.5,
      "social_solo": 0.4,
      "mood_relaxed": 0.7,
      "mood_nostalgic": 0.6,
      "location_home": 0.8,
      "location_indoor": 0.9,
      "energy_low": 0.4
    }
  },
  {
    "text": "سمنوی شیرین و مقوی",
    "category": "food_drink",
    "subcategory": "seasonal_cultural_specials",
    "preferencesJson": {
      "temp_cold": 0.8,
      "temp_cool": 0.6,
      "weather_cloudy": 0.5,
      "weather_rain": 0.6,
      "time_evening": 0.6,
      "season_spring": 1.0,
      "season_winter": 0.6,
      "cultural_tradition": 1.0,
      "social_family": 0.6,
      "social_group": 0.5,
      "mood_happy": 0.5,
      "mood_nostalgic": 0.6,
      "location_indoor": 0.6,
      "energy_low": 0.4
    }
  },
  {
    "text": "حلوای گندم تیره و خوش‌عطر",
    "category": "food_drink",
    "subcategory": "seasonal_cultural_specials",
    "preferencesJson": {
      "temp_cold": 0.8,
      "temp_cool": 0.6,
      "weather_rain": 0.5,
      "weather_cloudy": 0.4,
      "time_evening": 0.6,
      "season_winter": 0.7,
      "season_autumn": 0.6,
      "cultural_tradition": 0.8,
      "social_family": 0.5,
      "mood_nostalgic": 0.6,
      "location_indoor": 0.7,
      "energy_low": 0.3
    }
  },
  {
    "text": "کلوچه فومنی گرم با مغز گردو",
    "category": "food_drink",
    "subcategory": "seasonal_cultural_specials",
    "preferencesJson": {
      "temp_cold": 0.7,
      "temp_cool": 0.6,
      "weather_cloudy": 0.5,
      "weather_rain": 0.5,
      "time_evening": 0.7,
      "season_autumn": 0.7,
      "season_winter": 0.6,
      "cultural_tradition": 0.7,
      "social_group": 0.5,
      "social_family": 0.5,
      "mood_relaxed": 0.5,
      "mood_happy": 0.4,
      "location_indoor": 0.6,
      "energy_low": 0.3
    }
  },
  {
    "text": "باسلوق نرم با پودر نارگیل",
    "category": "food_drink",
    "subcategory": "seasonal_cultural_specials",
    "preferencesJson": {
      "temp_cool": 0.5,
      "temp_cold": 0.6,
      "weather_cloudy": 0.4,
      "time_evening": 0.6,
      "season_autumn": 0.5,
      "season_winter": 0.5,
      "day_holiday": 0.6,
      "cultural_tradition": 0.7,
      "social_family": 0.5,
      "social_group": 0.4,
      "mood_happy": 0.5,
      "location_indoor": 0.6,
      "energy_low": 0.3
    }
  },
  {
    "text": "سوپ مرغ و هویج سبک",
    "category": "food_drink",
    "subcategory": "seasonal_cultural_specials",
    "preferencesJson": {
      "temp_extreme_cold": 1.0,
      "temp_cold": 0.8,
      "temp_hot": -0.8,
      "weather_rain": 0.7,
      "weather_cloudy": 0.6,
      "time_evening": 0.7,
      "season_winter": 0.8,
      "season_autumn": 0.7,
      "cultural_tradition": 0.6,
      "social_family": 0.5,
      "mood_relaxed": 0.6,
      "location_home": 0.8,
      "location_indoor": 0.8,
      "energy_low": 0.3
    }
  },
  {
    "text": "کوکوی سبزی با گردو و زرشک",
    "category": "food_drink",
    "subcategory": "seasonal_cultural_specials",
    "preferencesJson": {
      "temp_warm": 0.5,
      "temp_cool": 0.4,
      "weather_clear": 0.4,
      "weather_partly_cloudy": 0.3,
      "time_afternoon": 0.5,
      "season_spring": 0.8,
      "season_autumn": 0.6,
      "cultural_tradition": 0.6,
      "social_family": 0.4,
      "social_group": 0.4,
      "mood_relaxed": 0.4,
      "location_indoor": 0.5,
      "energy_medium": 0.3
    }
  },
  {
    "text": "شربت بهارنارنج با تخم‌شربتی",
    "category": "food_drink",
    "subcategory": "seasonal_cultural_specials",
    "preferencesJson": {
      "temp_hot": 0.9,
      "temp_warm": 0.8,
      "temp_cold": -0.7,
      "weather_clear": 0.9,
      "weather_partly_cloudy": 0.6,
      "humidity_dry": 0.6,
      "time_afternoon": 0.7,
      "season_spring": 1.0,
      "season_summer": 0.8,
      "cultural_tradition": 0.7,
      "social_family": 0.4,
      "mood_happy": 0.6,
      "location_outdoor": 0.6,
      "energy_medium": 0.4
    }
  },
  {
    "text": "ژله زعفرانی با پسته",
    "category": "food_drink",
    "subcategory": "seasonal_cultural_specials",
    "preferencesJson": {
      "temp_warm": 0.5,
      "temp_hot": 0.6,
      "temp_cold": -0.5,
      "weather_clear": 0.5,
      "weather_partly_cloudy": 0.4,
      "time_evening": 0.5,
      "season_summer": 0.6,
      "season_spring": 0.5,
      "cultural_tradition": 0.7,
      "social_group": 0.5,
      "social_family": 0.4,
      "mood_happy": 0.5,
      "location_indoor": 0.5,
      "energy_low": 0.3
    }
  },
  {
    "text": "کاچی زعفرانی مقوی با مغزیجات",
    "category": "food_drink",
    "subcategory": "seasonal_cultural_specials",
    "preferencesJson": {
      "temp_extreme_cold": 1.0,
      "temp_cold": 0.9,
      "temp_hot": -0.9,
      "weather_snow": 0.8,
      "weather_rain": 0.7,
      "time_evening": 0.7,
      "season_winter": 1.0,
      "season_autumn": 0.7,
      "cultural_tradition": 0.9,
      "social_family": 0.6,
      "mood_relaxed": 0.6,
      "mood_nostalgic": 0.6,
      "location_home": 0.8,
      "location_indoor": 0.8,
      "energy_low": 0.4
    }
  },
  {
    "text": "حلوای هویج با هل و گلاب",
    "category": "food_drink",
    "subcategory": "seasonal_cultural_specials",
    "preferencesJson": {
      "temp_cold": 0.8,
      "temp_cool": 0.6,
      "temp_hot": -0.7,
      "weather_cloudy": 0.5,
      "weather_rain": 0.6,
      "time_evening": 0.7,
      "season_autumn": 0.7,
      "season_winter": 0.7,
      "cultural_tradition": 0.8,
      "social_family": 0.5,
      "mood_nostalgic": 0.6,
      "mood_relaxed": 0.5,
      "location_indoor": 0.7,
      "energy_low": 0.3
    }
  },
  {
    "text": "آش شلغم برای روزهای سرما",
    "category": "food_drink",
    "subcategory": "seasonal_cultural_specials",
    "preferencesJson": {
      "temp_extreme_cold": 1.0,
      "temp_cold": 0.9,
      "temp_hot": -1.0,
      "weather_snow": 0.9,
      "weather_rain": 0.7,
      "weather_cloudy": 0.6,
      "time_evening": 0.7,
      "season_winter": 1.0,
      "season_autumn": 0.7,
      "cultural_tradition": 0.7,
      "social_family": 0.6,
      "mood_relaxed": 0.6,
      "location_indoor": 0.9,
      "energy_low": 0.3
    }
  },
  {
    "text": "بستنی زعفرانی با پسته فراوان",
    "category": "food_drink",
    "subcategory": "seasonal_cultural_specials",
    "preferencesJson": {
      "temp_hot": 1.0,
      "temp_warm": 0.7,
      "temp_cold": -0.9,
      "weather_clear": 0.9,
      "humidity_dry": 0.6,
      "time_afternoon": 0.8,
      "season_summer": 1.0,
      "season_spring": 0.4,
      "cultural_tradition": 0.6,
      "social_friends": 0.5,
      "mood_happy": 0.6,
      "location_outdoor": 0.6,
      "energy_medium": 0.4
    }
  },
  {
    "text": "ترخینه داغ با کشک",
    "category": "food_drink",
    "subcategory": "seasonal_cultural_specials",
    "preferencesJson": {
      "temp_extreme_cold": 1.0,
      "temp_cold": 0.9,
      "temp_hot": -1.0,
      "weather_snow": 0.9,
      "weather_rain": 0.8,
      "time_evening": 0.7,
      "season_winter": 1.0,
      "season_autumn": 0.7,
      "cultural_tradition": 0.8,
      "social_family": 0.5,
      "mood_relaxed": 0.6,
      "location_indoor": 0.8,
      "energy_low": 0.3
    }
  },
  {
    "text": "شربت زرشک و زعفران خنک",
    "category": "food_drink",
    "subcategory": "seasonal_cultural_specials",
    "preferencesJson": {
      "temp_hot": 0.9,
      "temp_warm": 0.7,
      "temp_cold": -0.7,
      "weather_clear": 0.8,
      "weather_partly_cloudy": 0.6,
      "humidity_dry": 0.6,
      "time_afternoon": 0.7,
      "season_summer": 0.8,
      "season_spring": 0.5,
      "cultural_tradition": 0.6,
      "social_family": 0.4,
      "mood_happy": 0.6,
      "location_outdoor": 0.6,
      "energy_medium": 0.4
    }
  },
  {
    "text": "حلوا شکری نرم و تازه",
    "category": "food_drink",
    "subcategory": "seasonal_cultural_specials",
    "preferencesJson": {
      "temp_cool": 0.5,
      "temp_cold": 0.6,
      "weather_cloudy": 0.4,
      "weather_rain": 0.4,
      "time_evening": 0.6,
      "season_winter": 0.6,
      "season_autumn": 0.5,
      "cultural_tradition": 0.7,
      "social_family": 0.5,
      "mood_nostalgic": 0.5,
      "location_indoor": 0.6,
      "energy_low": 0.3
    }
  },
  {
    "text": "قطاب یزدی با پودر قند",
    "category": "food_drink",
    "subcategory": "seasonal_cultural_specials",
    "preferencesJson": {
      "temp_cool": 0.6,
      "temp_cold": 0.6,
      "weather_cloudy": 0.4,
      "weather_rain": 0.5,
      "time_evening": 0.7,
      "season_autumn": 0.6,
      "season_winter": 0.6,
      "day_holiday": 0.8,
      "cultural_tradition": 0.9,
      "social_group": 0.6,
      "social_family": 0.5,
      "mood_happy": 0.6,
      "location_indoor": 0.6,
      "energy_low": 0.3
    }
  },
  {
    "text": "شربت سکنجبین و کاسنی برای خنکی",
    "category": "food_drink",
    "subcategory": "seasonal_cultural_specials",
    "preferencesJson": {
      "temp_hot": 1.0,
      "temp_warm": 0.8,
      "temp_cold": -0.8,
      "weather_clear": 1.0,
      "humidity_dry": 0.7,
      "time_afternoon": 0.8,
      "season_summer": 1.0,
      "season_spring": 0.6,
      "cultural_tradition": 0.6,
      "social_family": 0.4,
      "mood_happy": 0.5,
      "location_outdoor": 0.6,
      "energy_medium": 0.4
    }
  }
]
